MANIFEST.in
README.md
VERSION
requirements.txt
setup.cfg
setup.py
rhasspy_snips_nlu_hermes.egg-info/PKG-INFO
rhasspy_snips_nlu_hermes.egg-info/SOURCES.txt
rhasspy_snips_nlu_hermes.egg-info/dependency_links.txt
rhasspy_snips_nlu_hermes.egg-info/entry_points.txt
rhasspy_snips_nlu_hermes.egg-info/requires.txt
rhasspy_snips_nlu_hermes.egg-info/top_level.txt
rhasspysnips_nlu_hermes/__init__.py
rhasspysnips_nlu_hermes/__main__.py